[
  {
    "time": "00:00",
    "visits": 2025
  },
  {
    "time": "01:00",
    "visits": 1882
  },
  {
    "time": "02:00",
    "visits": 1809
  },
  {
    "time": "03:00",
    "visits": 1322
  },
  {
    "time": "04:00",
    "visits": 2122
  },
  {
    "time": "05:00",
    "visits": 1522
  },
  {
    "time": "06:00",
    "visits": 3122
  },
  {
    "time": "07:00",
    "visits": 1322
  },
  {
    "time": "08:00",
    "visits": 22
  },
  {
    "time": "09:00",
    "visits": 5122
  },
  {
    "time": "10:00",
    "visits": 0
  },
  {
    "time": "11:00",
    "visits": 1245
  },
  {
    "time": "12:00",
    "visits": 4312
  },
  {
    "time": "13:00",
    "visits": 1234
  },
  {
    "time": "14:00",
    "visits": 4112
  },
  {
    "time": "15:00",
    "visits": 1111
  },
  {
    "time": "16:00",
    "visits": 1122
  },
  {
    "time": "17:00",
    "visits": 1241
  },
  {
    "time": "18:00",
    "visits": 1122
  },
  {
    "time": "19:00",
    "visits": 1122
  },
  {
    "time": "20:00",
    "visits": 4124
  },
  {
    "time": "21:00",
    "visits": 2312
  },
  {
    "time": "22:00",
    "visits": 1231
  },
  {
    "time": "23:00",
    "visits": 1122
  },
  {
    "time": "24:00",
    "visits": 1122
  }
]